simple_rsa/__init__.py
simple_rsa-1.1.0.dist-info/LICENSE.txt
simple_rsa-1.1.0.dist-info/METADATA
simple_rsa-1.1.0.dist-info/WHEEL
simple_rsa-1.1.0.dist-info/top_level.txt
simple_rsa-1.1.0.dist-info/RECORD
