Metadata-Version: 2.1
Name: simple-rsa
Version: 1.1.0
Summary: A straightforward API to perform basic RSA-based operations..
Home-page: https://github.com/christophevg/py-simple-rsa
Author: Christophe VG
License: MIT
Keywords: RSA signing
Platform: UNKNOWN
Classifier: Environment :: Console
Classifier: Development Status :: 5 - Production/Stable
Classifier: Intended Audience :: Developers
Classifier: Intended Audience :: System Administrators
Classifier: Topic :: Software Development
Classifier: License :: OSI Approved :: MIT License
Classifier: Programming Language :: Python
Classifier: Programming Language :: Python :: 3.7
Requires-Dist: cryptography
